cdktf_cdktf_provider_azuread/__init__.py
cdktf_cdktf_provider_azuread/py.typed
cdktf_cdktf_provider_azuread/_jsii/__init__.py
cdktf_cdktf_provider_azuread/_jsii/provider-azuread@14.2.0.jsii.tgz
cdktf_cdktf_provider_azuread/access_package/__init__.py
cdktf_cdktf_provider_azuread/access_package_assignment_policy/__init__.py
cdktf_cdktf_provider_azuread/access_package_catalog/__init__.py
cdktf_cdktf_provider_azuread/access_package_catalog_role_assignment/__init__.py
cdktf_cdktf_provider_azuread/access_package_resource_catalog_association/__init__.py
cdktf_cdktf_provider_azuread/access_package_resource_package_association/__init__.py
cdktf_cdktf_provider_azuread/administrative_unit/__init__.py
cdktf_cdktf_provider_azuread/administrative_unit_member/__init__.py
cdktf_cdktf_provider_azuread/administrative_unit_role_member/__init__.py
cdktf_cdktf_provider_azuread/app_role_assignment/__init__.py
cdktf_cdktf_provider_azuread/application/__init__.py
cdktf_cdktf_provider_azuread/application_api_access/__init__.py
cdktf_cdktf_provider_azuread/application_app_role/__init__.py
cdktf_cdktf_provider_azuread/application_certificate/__init__.py
cdktf_cdktf_provider_azuread/application_fallback_public_client/__init__.py
cdktf_cdktf_provider_azuread/application_federated_identity_credential/__init__.py
cdktf_cdktf_provider_azuread/application_from_template/__init__.py
cdktf_cdktf_provider_azuread/application_identifier_uri/__init__.py
cdktf_cdktf_provider_azuread/application_known_clients/__init__.py
cdktf_cdktf_provider_azuread/application_optional_claims/__init__.py
cdktf_cdktf_provider_azuread/application_owner/__init__.py
cdktf_cdktf_provider_azuread/application_password/__init__.py
cdktf_cdktf_provider_azuread/application_permission_scope/__init__.py
cdktf_cdktf_provider_azuread/application_pre_authorized/__init__.py
cdktf_cdktf_provider_azuread/application_redirect_uris/__init__.py
cdktf_cdktf_provider_azuread/application_registration/__init__.py
cdktf_cdktf_provider_azuread-14.2.0.dist-info/LICENSE
cdktf_cdktf_provider_azuread-14.2.0.dist-info/METADATA
cdktf_cdktf_provider_azuread-14.2.0.dist-info/WHEEL
cdktf_cdktf_provider_azuread-14.2.0.dist-info/top_level.txt
cdktf_cdktf_provider_azuread-14.2.0.dist-info/RECORD
